{
  "annotations": {
    "list": []
  },
  "editable": true,
  "fiscalYearStartMonth": 0,
  "graphTooltip": 0,
  "id": null,
  "links": [],
  "liveNow": false,
  "panels": [
    {
      "datasource": {
        "type": "prometheus",
        "uid": "prometheus"
      },
      "fieldConfig": {
        "defaults": {
          "color": {
            "mode": "palette-classic"
          },
          "custom": {
            "axisCenteredZero": false,
            "axisColorMode": "text",
            "axisLabel": "",
            "axisPlacement": "auto",
            "drawStyle": "line",
            "fillOpacity": 10,
            "gradientMode": "none",
            "lineInterpolation": "linear",
            "lineWidth": 1,
            "pointSize": 5,
            "scaleDistribution": {
              "type": "linear"
            },
            "showPoints": "never",
            "spanNulls": true,
            "stacking": {
              "group": "A",
              "mode": "none"
            }
          },
          "unit": "reqps"
        },
        "overrides": []
      },
      "gridPos": {
        "h": 8,
        "w": 12,
        "x": 0,
        "y": 0
      },
      "id": 1,
      "options": {
        "legend": {
          "displayMode": "list",
          "placement": "bottom",
          "showLegend": true
        },
        "tooltip": {
          "mode": "multi"
        }
      },
      "targets": [
        {
          "expr": "sum by (module, handler) (rate(app_http_requests_total[1m]))",
          "legendFormat": "{{module}}/{{handler}}",
          "refId": "A"
        }
      ],
      "title": "Request rate by handler",
      "type": "timeseries"
    },
    {
      "datasource": {
        "type": "prometheus",
        "uid": "prometheus"
      },
      "fieldConfig": {
        "defaults": {
          "color": {
            "mode": "palette-classic"
          },
          "custom": {
            "axisCenteredZero": false,
            "drawStyle": "line",
            "fillOpacity": 10,
            "lineWidth": 1,
            "showPoints": "never"
          },
          "unit": "s"
        },
        "overrides": []
      },
      "gridPos": {
        "h": 8,
        "w": 12,
        "x": 12,
        "y": 0
      },
      "id": 2,
      "options": {
        "legend": {
          "displayMode": "list",
          "placement": "bottom",
          "showLegend": true
        },
        "tooltip": {
          "mode": "multi"
        }
      },
      "targets": [
        {
          "expr": "histogram_quantile(0.95, sum by (le, module, handler) (rate(app_http_request_duration_seconds_bucket[5m])))",
          "legendFormat": "p95 {{module}}/{{handler}}",
          "refId": "A"
        },
        {
          "expr": "histogram_quantile(0.50, sum by (le, module, handler) (rate(app_http_request_duration_seconds_bucket[5m])))",
          "legendFormat": "p50 {{module}}/{{handler}}",
          "refId": "B"
        }
      ],
      "title": "Handler latency (p50 / p95)",
      "type": "timeseries"
    },
    {
      "datasource": {
        "type": "prometheus",
        "uid": "prometheus"
      },
      "fieldConfig": {
        "defaults": {
          "color": {
            "mode": "palette-classic"
          },
          "custom": {
            "drawStyle": "line",
            "fillOpacity": 10,
            "lineWidth": 1,
            "showPoints": "never"
          },
          "unit": "short"
        },
        "overrides": []
      },
      "gridPos": {
        "h": 8,
        "w": 12,
        "x": 0,
        "y": 8
      },
      "id": 3,
      "options": {
        "legend": {
          "displayMode": "list",
          "placement": "bottom",
          "showLegend": true
        },
        "tooltip": {
          "mode": "multi"
        }
      },
      "targets": [
        {
          "expr": "sum by (module, handler) (app_http_requests_in_flight)",
          "legendFormat": "{{module}}/{{handler}}",
          "refId": "A"
        }
      ],
      "title": "In-flight requests",
      "type": "timeseries"
    },
    {
      "datasource": {
        "type": "prometheus",
        "uid": "prometheus"
      },
      "fieldConfig": {
        "defaults": {
          "color": {
            "mode": "palette-classic"
          },
          "custom": {
            "drawStyle": "line",
            "fillOpacity": 10,
            "lineWidth": 1,
            "showPoints": "never"
          },
          "unit": "percentunit"
        },
        "overrides": []
      },
      "gridPos": {
        "h": 8,
        "w": 12,
        "x": 12,
        "y": 8
      },
      "id": 4,
      "options": {
        "legend": {
          "displayMode": "list",
          "placement": "bottom",
          "showLegend": true
        },
        "tooltip": {
          "mode": "multi"
        }
      },
      "targets": [
        {
          "expr": "sum by (module, handler) (rate(app_http_requests_total{status=\"error\"}[5m])) / clamp_min(sum by (module, handler) (rate(app_http_requests_total[5m])), 1)",
          "legendFormat": "{{module}}/{{handler}}",
          "refId": "A"
        }
      ],
      "title": "Error ratio",
      "type": "timeseries"
    }
  ],
  "refresh": "10s",
  "schemaVersion": 38,
  "style": "dark",
  "tags": [
    "sample_project"
  ],
  "templating": {
    "list": []
  },
  "time": {
    "from": "now-1h",
    "to": "now"
  },
  "timepicker": {},
  "timezone": "",
  "title": "Sample Project Overview",
  "uid": "sample-project-overview",
  "version": 1,
  "weekStart": ""
}